warehouses/__init__.py
warehouses/bigquery/__init__.py
warehouses/bigquery/auth.py
warehouses/bigquery/bigquery.py
warehouses-0.1.3.dist-info/LICENSE
warehouses-0.1.3.dist-info/WHEEL
warehouses-0.1.3.dist-info/METADATA
warehouses-0.1.3.dist-info/RECORD
